sphinxcontrib_django/__init__.py
sphinxcontrib_django/roles.py
sphinxcontrib_django/docstrings/__init__.py
sphinxcontrib_django/docstrings/attributes.py
sphinxcontrib_django/docstrings/classes.py
sphinxcontrib_django/docstrings/config.py
sphinxcontrib_django/docstrings/data.py
sphinxcontrib_django/docstrings/field_utils.py
sphinxcontrib_django/docstrings/methods.py
sphinxcontrib_django/docstrings/patches.py
sphinxcontrib_django-2.5.dist-info/AUTHORS
sphinxcontrib_django-2.5.dist-info/LICENSE
sphinxcontrib_django-2.5.dist-info/METADATA
sphinxcontrib_django-2.5.dist-info/WHEEL
sphinxcontrib_django-2.5.dist-info/top_level.txt
sphinxcontrib_django-2.5.dist-info/RECORD
